[{
        "tag": ["glasses"],
        "review": "Sunflower E-Shop.",
        "name": "SolarView Classic Shades",
        "rating": 5,
        "img": "/glasses1.png"

    },
    {
        "tag": ["glasses"],
        "review": "GreenByte Store",
        "name": " AquaBlue Sports ",
        "rating": 4,

        "img": "/glasses2.png"
    },
    {
        "tag": ["glasses"],
        "review": "Datastream Mako",
        "name": "RetroSpecs Vintage Frames",
        "rating": 2.5,
        "img": "/glasses2.png"
    },
    {
        "tag": ["blender"],
        "review": "Sunflower E-Shop",
        "name": " PowerMax 5000",
        "rating": 5,
        "img": "/blender1.png"
    },
    {
        "tag": ["blender"],
        "review": "DigitalSunset",
        "name": "EcoBlend 300",
        "rating": 3,
        "img": "/blender2.png"
    },
    {
        "tag": ["blender"],
        "review": "GreenByte Store",
        "name": "Multiblend Deluxe 800 ",
        "rating": 4,
        "img": "/blender3.png"
    },
    {
        "tag": ["microwave"],
        "review": "GreenByte Store",
        "name": " QuickHeat Compact Microwave",
        "rating": 5,
        "img": "/microwave1.png"
    },
    {
        "tag": ["microwave"],
        "review": "DigitalSunset",
        "name": "ChefPro Digital Microwave",
        "rating": 4.5,
        "img": "/microwave2.png"
    },
    {
        "tag": ["microwave"],
        "review": "Datastream Mako",
        "name": "EconoWave Basic Microwave ",
        "rating": 3.5,
        "img": "/microwave3.png"
    },
    {
        "tag": ["hat"],
        "review": "GreenByte Store",
        "name": "UrbanTrend Fedora",
        "rating": 5,
        "img": "/hat1.png"
    },
    {
        "tag": ["hat"],
        "review": "Datastream Mako",
        "name": "AdventurePro Outdoor Hat",
        "rating": 4,
        "img": "/hat2.png"
    },
    {
        "tag": ["hat"],
        "review": "DigitalSunset",
        "name": "ClassicKnit Beanie",
        "rating": 3.5,
        "img": "/hat3.png"
    },
    {
        "tag": ["wine"],
        "review": "Datastream Mako",
        "name": "Château Prestige Cabernet Sauvignon",
        "rating": 5,
        "img": "/wine1.png"
    },
    {
        "tag": ["wine"],
        "review": "DigitalSunset",
        "name": "ValleyBreeze Pinot Noir",
        "rating": 5,
        "img": "/wine2.png"
    },
    {
        "tag": ["wine"],
        "review": "Sunflower E-Shop",
        "name": "GoldenHills Chardonnay",
        "rating": 3,
        "img": "/wine3.png"
    }
]